taxoniq/__init__.py
taxoniq/build.py
taxoniq/cli.py
taxoniq/tax_dump_readers.py
taxoniq/util.py
taxoniq/version.py
taxoniq/vendored/__init__.py
taxoniq-1.0.3.dist-info/LICENSE
taxoniq-1.0.3.dist-info/LICENSE.NCBI
taxoniq-1.0.3.dist-info/LICENSE.WIKIPEDIA
taxoniq-1.0.3.dist-info/METADATA
taxoniq-1.0.3.dist-info/WHEEL
taxoniq-1.0.3.dist-info/entry_points.txt
taxoniq-1.0.3.dist-info/top_level.txt
taxoniq-1.0.3.dist-info/RECORD
