Metadata-Version: 2.1
Name: taxoniq
Version: 1.0.3
Summary: Taxoniq: Taxon Information Query - fast, offline querying of NCBI Taxonomy and related data
Home-page: https://github.com/chanzuckerberg/taxoniq
Author: Andrey Kislyuk
Author-email: akislyuk@chanzuckerberg.com
License: MIT License
Project-URL: Documentation, https://chanzuckerberg.github.io/taxoniq
Project-URL: Source Code, https://github.com/chanzuckerberg/taxoniq
Project-URL: Issue Tracker, https://github.com/chanzuckerberg/taxoniq/issues
Platform: MacOS X
Platform: Posix
Classifier: Intended Audience :: Developers
Classifier: License :: OSI Approved :: MIT License
Classifier: Operating System :: MacOS :: MacOS X
Classifier: Operating System :: POSIX
Classifier: Programming Language :: Python
Classifier: Programming Language :: Python :: 3.8
Classifier: Programming Language :: Python :: 3.9
Classifier: Programming Language :: Python :: 3.10
Classifier: Programming Language :: Python :: 3.11
Classifier: Programming Language :: Python :: 3.12
Classifier: Topic :: Software Development :: Libraries :: Python Modules
License-File: LICENSE
License-File: LICENSE.NCBI
License-File: LICENSE.WIKIPEDIA
Requires-Dist: marisa-trie >=1.1.0
Requires-Dist: zstandard >=0.21.0
Requires-Dist: urllib3 >=1.26.5
Requires-Dist: ncbi-taxon-db >=2024.9.07
